ddsc/__init__.py
ddsc/info.py
ddsc/data/__init__.py
ddsc/data/data_preprocesser.py
ddsc/data/dataset_loader.py
ddsc/model/__init__.py
ddsc/model/trainer.py
ddsc/model/utils.py
ddsc-1.0.1.dist-info/METADATA
ddsc-1.0.1.dist-info/WHEEL
ddsc-1.0.1.dist-info/top_level.txt
ddsc-1.0.1.dist-info/RECORD
