Metadata-Version: 2.1
Name: ddsc
Version: 1.0.1
Summary: Data-Driven Shock Capturing
Home-page: UNKNOWN
Author: zoonature
Author-email: zoonature@snu.ac.kr
License: UNKNOWN
Platform: UNKNOWN
